finquant/__init__.py
finquant/asset.py
finquant/data_types.py
finquant/efficient_frontier.py
finquant/exceptions.py
finquant/market.py
finquant/minimise_fun.py
finquant/monte_carlo.py
finquant/moving_average.py
finquant/portfolio.py
finquant/quants.py
finquant/returns.py
finquant/stock.py
finquant/type_utilities.py
FinQuant-0.7.0.dist-info/LICENSE.txt
FinQuant-0.7.0.dist-info/METADATA
FinQuant-0.7.0.dist-info/WHEEL
FinQuant-0.7.0.dist-info/top_level.txt
FinQuant-0.7.0.dist-info/RECORD
