Metadata-Version: 2.1
Name: FinQuant
Version: 0.7.0
Summary: A program for financial portfolio management, analysis and optimisation
Home-page: https://github.com/fmilthaler/FinQuant
Download-URL: https://github.com/fmilthaler/FinQuant/archive/v0.7.0.tar.gz
Author: Frank Milthaler
Author-email: f.milthaler@gmail.com
License: MIT
Project-URL: Documentation, https://finquant.readthedocs.io
Keywords: finance,portfolio,investment,numerical,optimisation,monte carlo,efficient frontier,quantitative,quant
Classifier: Development Status :: 4 - Beta
Classifier: Intended Audience :: Education
Classifier: Intended Audience :: Financial and Insurance Industry
Classifier: Intended Audience :: Other Audience
Classifier: Intended Audience :: Science/Research
Classifier: Programming Language :: Python :: 3 :: Only
Classifier: Programming Language :: Python :: 3.10
Classifier: Programming Language :: Python :: 3.11
Classifier: License :: OSI Approved :: MIT License
Classifier: Operating System :: OS Independent
Requires-Python: >=3.10
License-File: LICENSE.txt
Requires-Dist: numpy >=1.22.0
Requires-Dist: scipy >=1.2.0
Requires-Dist: pandas >=2.0
Requires-Dist: matplotlib >=3.0
Requires-Dist: quandl >=3.4.5
Requires-Dist: yfinance >=0.1.43
Requires-Dist: scikit-learn >=1.3.0
Provides-Extra: cd
Requires-Dist: build ; extra == 'cd'
Requires-Dist: setuptools ; extra == 'cd'
Requires-Dist: wheel ; extra == 'cd'
Requires-Dist: twine ; extra == 'cd'
Provides-Extra: dev
Requires-Dist: black ; extra == 'dev'
Requires-Dist: mypy ; extra == 'dev'
Requires-Dist: isort ; extra == 'dev'
Requires-Dist: jupyter ; extra == 'dev'
Requires-Dist: notebook ; extra == 'dev'
Provides-Extra: docs
Requires-Dist: sphinx ==6.2.1 ; extra == 'docs'
Requires-Dist: sphinx-rtd-theme ==1.2.0 ; extra == 'docs'
Requires-Dist: sphinx-autodoc-typehints ; extra == 'docs'
Provides-Extra: test
Requires-Dist: pytest >=7.3.2 ; extra == 'test'
Requires-Dist: black ; extra == 'test'
Requires-Dist: mypy ; extra == 'test'
Requires-Dist: isort ; extra == 'test'
Requires-Dist: pylint ; extra == 'test'
Requires-Dist: pydantic ; extra == 'test'
